sffloat/__init__.py
sffloat/__version__.py
sffloat/sffloat.py
sffloat-0.2.0.dist-info/LICENSE
sffloat-0.2.0.dist-info/METADATA
sffloat-0.2.0.dist-info/WHEEL
sffloat-0.2.0.dist-info/top_level.txt
sffloat-0.2.0.dist-info/RECORD
